flake8_scout_rule/__init__.py
flake8_scout_rule/flake8_scout_rule.py
tests/__init__.py
tests/flake8_scout_rule_test.py
flake8_scout_rule-1.0.0.dist-info/LICENSE
flake8_scout_rule-1.0.0.dist-info/METADATA
flake8_scout_rule-1.0.0.dist-info/WHEEL
flake8_scout_rule-1.0.0.dist-info/entry_points.txt
flake8_scout_rule-1.0.0.dist-info/top_level.txt
flake8_scout_rule-1.0.0.dist-info/RECORD
