Metadata-Version: 2.1
Name: flake8_scout_rule
Version: 1.0.0
Summary: A Flake8 formatter that applies '# noqa: <errors>' annotations to flake8 violations found, helping to incrementally improve code quality.
Home-page: https://github.com/snackattas/flake8-scout-rule
Author: Zachary Attas
Author-email: zach.attas@gmail.com
License: MIT
Classifier: Framework :: Flake8
Classifier: License :: OSI Approved :: MIT License
Classifier: Programming Language :: Python
Classifier: Programming Language :: Python :: 3
Classifier: Programming Language :: Python :: 3.8
Classifier: Programming Language :: Python :: 3.9
Classifier: Programming Language :: Python :: 3.10
Classifier: Programming Language :: Python :: 3.11
Classifier: Programming Language :: Python :: 3.12
Classifier: Programming Language :: Python :: 3.13
Classifier: Topic :: Software Development :: Libraries :: Python Modules
Classifier: Topic :: Software Development :: Quality Assurance
License-File: LICENSE
Requires-Dist: flake8>=3.8.0
Requires-Dist: importlib-metadata; python_version < "3.7"
